mcp_md2xmind/__init__.py
mcp_md2xmind/server.py
mcp_md2xmind-0.1.0.dist-info/METADATA
mcp_md2xmind-0.1.0.dist-info/WHEEL
mcp_md2xmind-0.1.0.dist-info/top_level.txt
mcp_md2xmind-0.1.0.dist-info/RECORD
