Metadata-Version: 2.4
Name: mcp-md2xmind
Version: 0.1.0
Summary: Add your description here
Author: mengyu
Author-email: pengmengyu97@gmail.com
Requires-Python: >=3.6
Requires-Dist: fastmcp>=2.11.1
Requires-Dist: mcp[cli]>=1.12.3
Requires-Dist: md2xmind>=1.2.3
Requires-Dist: setuptools>=80.9.0
Requires-Dist: twine>=6.1.0
Requires-Dist: wheel>=0.45.1
Dynamic: author
Dynamic: author-email
Dynamic: requires-python
